{
  "themes": [
    {
      "id": "sur_mod_miui13_v1",
      "name": "SUR MOD MIUI13 V1",
      "options": [
        {
          "id": "sur_mod_miui13_v1_default",
          "name": "SUR MOD MIUI13 V1 Default",
          "previewImage": "w_0",
          "components": {
            "wallpaper": {
              "default": "w_0",
              "variants": [
                "w_0"
              ]
            },
            "lockscreen": "l_0",
            "wifi": [
              "stat_sys_wifi_signal_0",
              "stat_sys_wifi_signal_1",
              "stat_sys_wifi_signal_2",
              "stat_sys_wifi_signal_3",
              "stat_sys_wifi_signal_4",
              "status_bar_toggle_wifi_on",
              "status_bar_toggle_wifi_off"
            ],
            "signal": [
              "stat_sys_signal_0",
              "stat_sys_signal_1",
              "stat_sys_signal_2",
              "stat_sys_signal_3",
              "stat_sys_signal_4",
              "stat_sys_signal_5"
            ],
            "bluetooth": [
              "stat_sys_data_bluetooth",
              "stat_sys_data_bluetooth_in",
              "stat_sys_data_bluetooth_out",
              "stat_sys_data_bluetooth_inout",
              "stat_sys_data_bluetooth_connected"
            ],
            "charge": "stat_sys_battery_charging",
            "data": [
              "stat_sys_signal_data",
              "stat_sys_signal_in",
              "stat_sys_signal_out",
              "stat_sys_signal_inout",
              "stat_sys_signal_dual_data",
              "status_bar_toggle_data_on",
              "status_bar_toggle_data_off"
            ],
            "hotspot": [
              "stat_sys_wifi_ap_on",
              "stat_sys_wifi_ap"
            ],
            "airplane": "stat_sys_signal_flightmode",
            "ringer": [
              "stat_sys_ringer_silent",
              "stat_sys_ringer_vibrate"
            ],
            "battery": {
              "type": "sprite_sheet",
              "assetRoot": "assets/battery",
              "layout": "vertical",
              "frame": {
                "width": 83,
                "height": 60
              },
              "indexing": "top_to_bottom",
              "progressMapping": "linear",
              "modes": {
                "normal": {
                  "asset": "stat_sys_battery",
                  "frames": 20
                },
                "charging": {
                  "asset": "stat_sys_battery_charge",
                  "frames": 20
                },
                "digital": {
                  "asset": "stat_sys_battery_digital",
                  "frames": 20
                },
                "charge_digit": {
                  "asset": "stat_sys_battery_charge_digit",
                  "frames": 20
                },
                "power_save": {
                  "asset": "stat_sys_battery_power_save",
                  "frames": 20
                },
                "power_save_charge": {
                  "asset": "stat_sys_battery_power_save_charge",
                  "frames": 20
                }
              }
            }
          }
        }
      ]
    }
  ]
}
